UART_Project.srcs/sources_1/new/uart_design.v
`timescale 1ns / 1ps

// ============================================================================
// Module: Baud Rate Generator (16x Oversampling)
// ============================================================================
module baud_rate_generator #(
    parameter CLK_FREQ = 100_000_000,
    parameter BAUD_RATE = 115200
)(
    input wire clk,
    input wire reset,
    output reg tick // Generates a tick 16 times per bit
);
    // Calculate divisor for 16x oversampling
    // Example: 100MHz / (115200 * 16) = ~54 clocks per tick
    localparam integer DIVISOR = CLK_FREQ / (BAUD_RATE * 16);
    localparam integer COUNTER_WIDTH = $clog2(DIVISOR);
    
    reg [COUNTER_WIDTH-1:0] counter;
    
    always @(posedge clk) begin
        if (reset) begin
            counter <= 0;
            tick <= 1'b0;
        end else begin
            if (counter >= DIVISOR - 1) begin
                counter <= 0;
                tick <= 1'b1;
            end else begin
                counter <= counter + 1;
                tick <= 1'b0;
            end
        end
    end
endmodule

// ============================================================================
// Module: UART Transmitter
// ============================================================================
module uart_tx #(
    parameter DATA_WIDTH = 8
)(
    input wire clk,
    input wire reset,
    input wire tick,    // 16x tick input
    input wire start,
    input wire [DATA_WIDTH-1:0] data_in,
    output reg tx_serial,
    output reg busy
);

    localparam [1:0] IDLE  = 2'b00,
                     START = 2'b01,
                     DATA  = 2'b10,
                     STOP  = 2'b11;
    
    reg [1:0] state, next_state;
    reg [DATA_WIDTH-1:0] data_reg;
    reg [2:0] bit_counter;    
    reg [3:0] tick_counter;   
    
    // State Register
    always @(posedge clk) begin
        if (reset) state <= IDLE;
        else state <= next_state;
    end
    
    // Next State Logic
    always @(*) begin
        next_state = state;
        case (state)
            IDLE: begin
                if (start) next_state = START;
            end
            START: begin
                // Wait for 16 ticks (entire start bit duration)
                if (tick && tick_counter == 15) next_state = DATA;
            end
            DATA: begin
                // Wait for 16 ticks per bit, for 8 bits
                if (tick && tick_counter == 15 && bit_counter == 7) next_state = STOP;
            end
            STOP: begin
                // Stop bit duration
                if (tick && tick_counter == 15) next_state = IDLE;
            end
            default: next_state = IDLE;
        endcase
    end
    
    // Datapath
    always @(posedge clk) begin
        if (reset) begin
            tx_serial <= 1'b1;
            busy <= 1'b0;
            data_reg <= 0;
            bit_counter <= 0;
            tick_counter <= 0;
        end
        else begin
            case (state)
                IDLE: begin
                    tx_serial <= 1'b1;
                    busy <= 1'b0;
                    tick_counter <= 0;
                    bit_counter <= 0;
                    if (start) begin
                        data_reg <= data_in;
                        busy <= 1'b1;
                    end
                end
                
                START: begin
                    tx_serial <= 1'b0; // Start bit
                    busy <= 1'b1;
                    if (tick) tick_counter <= tick_counter + 1;
                end
                
                DATA: begin
                    tx_serial <= data_reg[0]; // LSB First
                    busy <= 1'b1;
                    if (tick) begin
                        tick_counter <= tick_counter + 1;
                        if (tick_counter == 15) begin
                            data_reg <= {1'b0, data_reg[DATA_WIDTH-1:1]}; // Shift
                            bit_counter <= bit_counter + 1;
                        end
                    end
                end
                
                STOP: begin
                    tx_serial <= 1'b1; // Stop bit
                    busy <= 1'b1;
                    if (tick) tick_counter <= tick_counter + 1;
                end
            endcase
        end
    end
endmodule

// ============================================================================
// Module: UART Receiver (FIXED SAMPLING)
// ============================================================================
module uart_rx #(
    parameter DATA_WIDTH = 8
)(
    input wire clk,
    input wire reset,
    input wire tick,      // 16x tick input
    input wire rx_serial,
    output reg [DATA_WIDTH-1:0] data_out,
    output reg data_ready,
    output reg framing_error
);

    localparam [1:0] IDLE         = 2'b00,
                     START_DETECT = 2'b01,
                     DATA_RECEIVE = 2'b10,
                     STOP_CHECK   = 2'b11;
    
    reg [1:0] state, next_state;
    reg [DATA_WIDTH-1:0] data_reg;
    reg [2:0] bit_counter;
    reg [3:0] sample_counter; 
    
    // Input Synchronization
    reg rx_sync1, rx_sync2;
    always @(posedge clk) begin
        if (reset) begin
            rx_sync1 <= 1'b1; rx_sync2 <= 1'b1;
        end else begin
            rx_sync1 <= rx_serial; rx_sync2 <= rx_sync1;
        end
    end
    
    // State Register
    always @(posedge clk) begin
        if (reset) state <= IDLE;
        else state <= next_state;
    end
    
    // Next State Logic
    always @(*) begin
        next_state = state;
        case (state)
            IDLE: begin
                if (!rx_sync2) next_state = START_DETECT;
            end
            START_DETECT: begin
                // Check middle of start bit (tick 7)
                if (tick && sample_counter == 7) begin
                    if (!rx_sync2) next_state = DATA_RECEIVE; 
                    else next_state = IDLE; 
                end
            end
            DATA_RECEIVE: begin
                // Wait for middle of last data bit
                if (tick && sample_counter == 15 && bit_counter == 7) next_state = STOP_CHECK;
            end
            STOP_CHECK: begin
                if (tick && sample_counter == 15) next_state = IDLE;
            end
            default: next_state = IDLE;
        endcase
    end
    
    // Datapath
    always @(posedge clk) begin
        if (reset) begin
            data_out <= 0;
            data_ready <= 0;
            framing_error <= 0;
            data_reg <= 0;
            bit_counter <= 0;
            sample_counter <= 0;
        end
        else begin
            data_ready <= 1'b0; // Default low
            
            case (state)
                IDLE: begin
                    bit_counter <= 0;
                    sample_counter <= 0;
                    framing_error <= 0;
                end
                
                START_DETECT: begin
                    if (tick) begin
                        if (sample_counter == 7) begin
                            // CRITICAL FIX: Reset counter so we wait exactly 16 ticks
                            // to reach the center of the first data bit.
                            sample_counter <= 0; 
                        end else begin
                            sample_counter <= sample_counter + 1;
                        end
                    end
                end
                
                DATA_RECEIVE: begin
                    if (tick) begin
                        sample_counter <= sample_counter + 1;
                        if (sample_counter == 15) begin
                            // Sample the bit in the middle
                            data_reg <= {rx_sync2, data_reg[DATA_WIDTH-1:1]};
                            bit_counter <= bit_counter + 1;
                            // sample_counter wraps to 0 naturally (4-bit)
                        end
                    end
                end
                
                STOP_CHECK: begin
                    if (tick) begin
                        sample_counter <= sample_counter + 1;
                        if (sample_counter == 15) begin
                            if (rx_sync2 == 1'b1) begin
                                data_out <= data_reg;
                                data_ready <= 1'b1;
                            end else begin
                                framing_error <= 1'b1;
                            end
                        end
                    end
                end
            endcase
        end
    end
endmodule

// ============================================================================
// Module: UART Top
// ============================================================================
module uart_top #(
    parameter CLK_FREQ = 100_000_000,
    parameter BAUD_RATE = 115200,
    parameter DATA_WIDTH = 8
)(
    input wire clk,
    input wire reset,
    input wire tx_start,
    input wire [DATA_WIDTH-1:0] tx_data_in,
    output wire tx_serial,
    output wire tx_busy,
    input wire rx_serial,
    output wire [DATA_WIDTH-1:0] rx_data_out,
    output wire rx_data_ready,
    output wire rx_framing_error
);

    wire tick; // 16x baud tick
    
    baud_rate_generator #(.CLK_FREQ(CLK_FREQ), .BAUD_RATE(BAUD_RATE)) baud_gen (
        .clk(clk), .reset(reset), .tick(tick)
    );
    
    uart_tx #(.DATA_WIDTH(DATA_WIDTH)) transmitter (
        .clk(clk), .reset(reset), .tick(tick),
        .start(tx_start), .data_in(tx_data_in),
        .tx_serial(tx_serial), .busy(tx_busy)
    );
    
    uart_rx #(.DATA_WIDTH(DATA_WIDTH)) receiver (
        .clk(clk), .reset(reset), .tick(tick),
        .rx_serial(rx_serial), .data_out(rx_data_out),
        .data_ready(rx_data_ready), .framing_error(rx_framing_error)
    );
endmodule

UART_Project.srcs/sim_1/new/uart_test.v
`timescale 1ns / 1ps

module uart_tb;

    // Simulation Parameters
    // We use standard 100MHz Clock and 115200 Baud
    parameter CLK_FREQ  = 100_000_000; 
    parameter BAUD_RATE = 115200;      
    parameter DATA_WIDTH = 8;
    
    // 100MHz = 10ns Period
    parameter CLK_PERIOD = 10; 

    // Signals
    reg clk;
    reg reset;
    reg tx_start;
    reg [DATA_WIDTH-1:0] tx_data_in;
    wire tx_serial;
    wire tx_busy;
    wire [DATA_WIDTH-1:0] rx_data_out;
    wire rx_data_ready;
    wire rx_framing_error;

    // DUT Instantiation
    uart_top #(
        .CLK_FREQ(CLK_FREQ),
        .BAUD_RATE(BAUD_RATE),
        .DATA_WIDTH(DATA_WIDTH)
    ) dut (
        .clk(clk),
        .reset(reset),
        .tx_start(tx_start),
        .tx_data_in(tx_data_in),
        .tx_serial(tx_serial),
        .tx_busy(tx_busy),
        .rx_serial(tx_serial), // Loopback TX to RX
        .rx_data_out(rx_data_out),
        .rx_data_ready(rx_data_ready),
        .rx_framing_error(rx_framing_error)
    );

    // Clock Generation
    initial begin
        clk = 0;
        forever #(CLK_PERIOD/2) clk = ~clk;
    end

    // Test Variables
    integer test_cnt = 0;
    integer fail_cnt = 0;

    // Monitor
    always @(posedge clk) begin
        if (rx_data_ready) begin
            $display("[%0t] Received: 0x%h", $time, rx_data_out);
        end
    end

    // Test Logic
    initial begin
        $dumpfile("uart_dump.vcd");
        $dumpvars(0, uart_tb);
        
        reset = 1;
        tx_start = 0;
        tx_data_in = 0;
        
        #(CLK_PERIOD * 10);
        reset = 0;
        #(CLK_PERIOD * 10);
        
        $display("Starting UART Test (Loopback)...");
        
        // Test 1: Send 0xA5
        send_byte(8'hA5);
        check_byte(8'hA5);
        
        // Test 2: Send 0x3C
        send_byte(8'h3C);
        check_byte(8'h3C);
        
        // Test 3: Send 0xFF
        send_byte(8'hFF);
        check_byte(8'hFF);

        if (fail_cnt == 0)
            $display("\nALL TESTS PASSED!");
        else
            $display("\nTESTS FAILED: %0d", fail_cnt);
            
        $finish;
    end
    
    // Tasks
    task send_byte;
        input [7:0] data;
        begin
            wait(!tx_busy);
            @(posedge clk);
            tx_data_in = data;
            tx_start = 1;
            @(posedge clk);
            tx_start = 0;
        end
    endtask
    
    task check_byte;
        input [7:0] expected;
        begin
            // Wait for data ready with timeout
            fork : wait_block
                begin
                    wait(rx_data_ready);
                    if (rx_data_out !== expected) begin
                        $display("FAIL: Expected 0x%h, Got 0x%h", expected, rx_data_out);
                        fail_cnt = fail_cnt + 1;
                    end else begin
                        $display("PASS: Got 0x%h", rx_data_out);
                    end
                    disable timeout_block;
                end
                begin : timeout_block
                    // Wait enough time for one byte (approx 10 bits * 8680ns per bit ~ 86us)
                    #1000000; 
                    $display("FAIL: Timeout waiting for 0x%h", expected);
                    fail_cnt = fail_cnt + 1;
                    disable wait_block;
                end
            join
        end
    endtask

endmodule

UART_Project.sim/sim_1/behav/xsim/uart_dump.vcd
$date
   Wed Nov 26 02:54:49 2025
$end
$version
  2018.2
$end
$timescale
  1ps
$end
$scope module uart_tb $end
$var reg 1 ! clk $end
$var reg 1 " reset $end
$var reg 1 # tx_start $end
$var reg 8 $ tx_data_in [7:0] $end
$var wire 1 % tx_serial $end
$var wire 1 & tx_busy $end
$var wire 8 ' rx_data_out [7:0] $end
$var wire 1 ( rx_data_ready $end
$var wire 1 ) rx_framing_error $end
$var integer 32 * test_cnt $end
$var integer 32 + fail_cnt $end
$var parameter 32 , CLK_FREQ [31:0] $end
$var parameter 32 - BAUD_RATE [31:0] $end
$var parameter 32 . DATA_WIDTH [31:0] $end
$var parameter 32 / CLK_PERIOD [31:0] $end
$scope module dut $end
$var wire 1 0 clk $end
$var wire 1 1 reset $end
$var wire 1 2 tx_start $end
$var wire 8 3 tx_data_in [7:0] $end
$var wire 1 % tx_serial $end
$var wire 1 & tx_busy $end
$var wire 1 % rx_serial $end
$var wire 8 ' rx_data_out [7:0] $end
$var wire 1 ( rx_data_ready $end
$var wire 1 ) rx_framing_error $end
$var wire 1 4 tick $end
$var parameter 32 5 CLK_FREQ [31:0] $end
$var parameter 32 6 BAUD_RATE [31:0] $end
$var parameter 32 7 DATA_WIDTH [31:0] $end
$scope module baud_gen $end
$var wire 1 0 clk $end
$var wire 1 1 reset $end
$var reg 1 8 tick $end
$var reg 6 9 counter [5:0] $end
$var parameter 32 : CLK_FREQ [31:0] $end
$var parameter 32 ; BAUD_RATE [31:0] $end
$var parameter 0 < DIVISOR $end
$var parameter 0 = COUNTER_WIDTH $end
$upscope $end
$scope module transmitter $end
$var wire 1 0 clk $end
$var wire 1 1 reset $end
$var wire 1 4 tick $end
$var wire 1 2 start $end
$var wire 8 3 data_in [7:0] $end
$var reg 1 > tx_serial $end
$var reg 1 ? busy $end
$var reg 2 @ state [1:0] $end
$var reg 2 A next_state [1:0] $end
$var reg 8 B data_reg [7:0] $end
$var reg 3 C bit_counter [2:0] $end
$var reg 4 D tick_counter [3:0] $end
$var parameter 32 E DATA_WIDTH [31:0] $end
$var parameter 2 F IDLE [1:0] $end
$var parameter 2 G START [1:0] $end
$var parameter 2 H DATA [1:0] $end
$var parameter 2 I STOP [1:0] $end
$upscope $end
$scope module receiver $end
$var wire 1 0 clk $end
$var wire 1 1 reset $end
$var wire 1 4 tick $end
$var wire 1 % rx_serial $end
$var reg 8 J data_out [7:0] $end
$var reg 1 K data_ready $end
$var reg 1 L framing_error $end
$var reg 2 M state [1:0] $end
$var reg 2 N next_state [1:0] $end
$var reg 8 O data_reg [7:0] $end
$var reg 3 P bit_counter [2:0] $end
$var reg 4 Q sample_counter [3:0] $end
$var reg 1 R rx_sync1 $end
$var reg 1 S rx_sync2 $end
$var parameter 32 T DATA_WIDTH [31:0] $end
$var parameter 2 U IDLE [1:0] $end
$var parameter 2 V START_DETECT [1:0] $end
$var parameter 2 W DATA_RECEIVE [1:0] $end
$var parameter 2 X STOP_CHECK [1:0] $end
$upscope $end
$upscope $end
$scope task send_byte $end
$var reg 8 Y data [7:0] $end
$upscope $end
$scope task check_byte $end
$var reg 8 Z expected [7:0] $end
$scope begin wait_block $end
$upscope $end
$upscope $end
$upscope $end
$enddefinitions $end
#0
$dumpvars
0!
1"
0#
b0 $
x%
x&
bx '
x(
x)
b0 *
b0 +
b101111101011110000100000000 ,
b11100001000000000 -
b1000 .
b1010 /
00
11
02
b0 3
x4
b101111101011110000100000000 5
b11100001000000000 6
b1000 7
x8
bx 9
b101111101011110000100000000 :
b11100001000000000 ;
b110110 <
b110 =
x>
x?
bx @
b0 A
bx B
bx C
bx D
b1000 E
b0 F
b1 G
b10 H
b11 I
bx J
xK
xL
bx M
bx N
bx O
bx P
bx Q
xR
xS
b1000 T
b0 U
b1 V
b10 W
b11 X
bx Y
bx Z
$end
#5000
1!
1%
0&
b0 '
0(
0)
10
04
08
b0 9
1>
0?
b0 @
b0 B
b0 C
b0 D
b0 J
0K
0L
b0 M
b0 N
b0 O
b0 P
b0 Q
1R
1S
#10000
0!
00
#15000
1!
10
#20000
0!
00
#25000
1!
10
#30000
0!
00
#35000
1!
10
#40000
0!
00
#45000
1!
10
#50000
0!
00
#55000
1!
10
#60000
0!
00
#65000
1!
10
#70000
0!
00
#75000
1!
10
#80000
0!
00
#85000
1!
10
#90000
0!
00
#95000
1!
10
#100000
0!
0"
00
01
#105000
1!
10
b1 9
#110000
0!
00
#115000
1!
10
b10 9
#120000
0!
00
#125000
1!
10
b11 9
#130000
0!
00
#135000
1!
10
b100 9
#140000
0!
00
#145000
1!
10
b101 9
#150000
0!
00
#155000
1!
10
b110 9
#160000
0!
00
#165000
1!
10
b111 9
#170000
0!
00
#175000
1!
10
b1000 9
#180000
0!
00
#185000
1!
10
b1001 9
#190000
0!
00
#195000
1!
10
b1010 9
#200000
0!
00
b10100101 Y
#205000
1!
1#
b10100101 $
1&
10
12
b10100101 3
b1011 9
1?
b1 A
b10100101 B
#210000
0!
00
#215000
1!
0#
0&
10
02
b1100 9
0?
b1 @
b1 A
b10100101 Z
#220000
0!
00
#225000
1!
0%
1&
10
b1101 9
0>
1?
#230000
0!
00
#235000
1!
10
b1110 9
0R
#240000
0!
00
#245000
1!
10
b1111 9
b1 N
0S
#250000
0!
00
#255000
1!
10
b10000 9
b1 M
#260000
0!
00
#265000
1!
10
b10001 9
#270000
0!
00
#275000
1!
10
b10010 9
#280000
0!
00
#285000
1!
10
b10011 9
#290000
0!
00
#295000
1!
10
b10100 9
#300000
0!
00
#305000
1!
10
b10101 9
#310000
0!
00
#315000
1!
10
b10110 9
#320000
0!
00
#325000
1!
10
b10111 9
#330000
0!
00
#335000
1!
10
b11000 9
#340000
0!
00
#345000
1!
10
b11001 9
#350000
0!
00
#355000
1!
10
b11010 9
#360000
0!
00
#365000
1!
10
b11011 9
#370000
0!
00
#375000
1!
10
b11100 9
#380000
0!
00
#385000
1!
10
b11101 9
#390000
0!
00
#395000
1!
10
b11110 9
#400000
0!
00
#405000
1!
10
b11111 9
#410000
0!
00
#415000
1!
10
b100000 9
#420000
0!
00
#425000
1!
10
b100001 9
#430000
0!
00
#435000
1!
10
b100010 9
#440000
0!
00
#445000
1!
10
b100011 9
#450000
0!
00
#455000
1!
10
b100100 9
#460000
0!
00
#465000
1!
10
b100101 9
#470000
0!
00
#475000
1!
10
b100110 9
#480000
0!
00
#485000
1!
10
b100111 9
#490000
0!
00
#495000
1!
10
b101000 9
#500000
0!
00
#505000
1!
10
b101001 9
#510000
0!
00
#515000
1!
10
b101010 9
#520000
0!
00
#525000
1!
10
b101011 9
#530000
0!
00
#535000
1!
10
b101100 9
#540000
0!
00
#545000
1!
10
b101101 9
#550000
0!
00
#555000
1!
10
b101110 9
#560000
0!
00
#565000
1!
10
b101111 9
#570000
0!
00
#575000
1!
10
b110000 9
#580000
0!
00
#585000
1!
10
b110001 9
#590000
0!
00
#595000
1!
10
b110010 9
#600000
0!
00
#605000
1!
10
b110011 9
#610000
0!
00
#615000
1!
10
b110100 9
#620000
0!
00
#625000
1!
10
b110101 9
#630000
0!
00
#635000
1!
10
14
18
b0 9
#640000
0!
00
#645000
1!
10
04
08
b1 9
b1 D
b1 Q
#650000
0!
00
#655000
1!
10
b10 9
#660000
0!
00
#665000
1!
10
b11 9
#670000
0!
00
#675000
1!
10
b100 9
#680000
0!
00
#685000
1!
10
b101 9
#690000
0!
00
#695000
1!
10
b110 9
#700000
0!
00
#705000
1!
10
b111 9
#710000
0!
00
#715000
1!
10
b1000 9
#720000
0!
00
#725000
1!
10
b1001 9
#730000
0!
00
#735000
1!
10
b1010 9
#740000
0!
00
#745000
1!
10
b1011 9
#750000
0!
00
#755000
1!
10
b1100 9
#760000
0!
00
#765000
1!
10
b1101 9
#770000
0!
00
#775000
1!
10
b1110 9
#780000
0!
00
#785000
1!
10
b1111 9
#790000
0!
00
#795000
1!
10
b10000 9
#800000
0!
00
#805000
1!
10
b10001 9
#810000
0!
00
#815000
1!
10
b10010 9
#820000
0!
00
#825000
1!
10
b10011 9
#830000
0!
00
#835000
1!
10
b10100 9
#840000
0!
00
#845000
1!
10
b10101 9
#850000
0!
00
#855000
1!
10
b10110 9
#860000
0!
00
#865000
1!
10
b10111 9
#870000
0!
00
#875000
1!
10
b11000 9
#880000
0!
00
#885000
1!
10
b11001 9
#890000
0!
00
#895000
1!
10
b11010 9
#900000
0!
00
#905000
1!
10
b11011 9
#910000
0!
00
#915000
1!
10
b11100 9
#920000
0!
00
#925000
1!
10
b11101 9
#930000
0!
00
#935000
1!
10
b11110 9
#940000
0!
00
#945000
1!
10
b11111 9
#950000
0!
00
#955000
1!
10
b100000 9
#960000
0!
00
#965000
1!
10
b100001 9
#970000
0!
00
#975000
1!
10
b100010 9
#980000
0!
00
#985000
1!
10
b100011 9
#990000
0!
00
#995000
1!
10
b100100 9
#1000000
0!
00
#1005000
1!
10
b100101 9
#1010000
0!
00
#1015000
1!
10
b100110 9
#1020000
0!
00
#1025000
1!
10
b100111 9
#1030000
0!
00
#1035000
1!
10
b101000 9
#1040000
0!
00
#1045000
1!
10
b101001 9
#1050000
0!
00
#1055000
1!
10
b101010 9
#1060000
0!
00
#1065000
1!
10
b101011 9
#1070000
0!
00
#1075000
1!
10
b101100 9
#1080000
0!
00
#1085000
1!
10
b101101 9
#1090000
0!
00
#1095000
1!
10
b101110 9
#1100000
0!
00
#1105000
1!
10
b101111 9
#1110000
0!
00
#1115000
1!
10
b110000 9
#1120000
0!
00
#1125000
1!
10
b110001 9
#1130000
0!
00
#1135000
1!
10
b110010 9
#1140000
0!
00
#1145000
1!
10
b110011 9
#1150000
0!
00
#1155000
1!
10
b110100 9
#1160000
0!
00
#1165000
1!
10
b110101 9
#1170000
0!
00
#1175000
1!
10
14
18
b0 9
#1180000
0!
00
#1185000
1!
10
04
08
b1 9
b10 D
b10 Q
#1190000
0!
00
#1195000
1!
10
b10 9
#1200000
0!
00
#1205000
1!
10
b11 9
#1210000
0!
00
#1215000
1!
10
b100 9
#1220000
0!
00
#1225000
1!
10
b101 9
#1230000
0!
00
#1235000
1!
10
b110 9
#1240000
0!
00
#1245000
1!
10
b111 9
#1250000
0!
00
#1255000
1!
10
b1000 9
#1260000
0!
00
#1265000
1!
10
b1001 9
#1270000
0!
00
#1275000
1!
10
b1010 9
#1280000
0!
00
#1285000
1!
10
b1011 9
#1290000
0!
00
#1295000
1!
10
b1100 9
#1300000
0!
00
#1305000
1!
10
b1101 9
#1310000
0!
00
#1315000
1!
10
b1110 9
#1320000
0!
00
#1325000
1!
10
b1111 9
#1330000
0!
00
#1335000
1!
10
b10000 9
#1340000
0!
00
#1345000
1!
10
b10001 9
#1350000
0!
00
#1355000
1!
10
b10010 9
#1360000
0!
00
#1365000
1!
10
b10011 9
#1370000
0!
00
#1375000
1!
10
b10100 9
#1380000
0!
00
#1385000
1!
10
b10101 9
#1390000
0!
00
#1395000
1!
10
b10110 9
#1400000
0!
00
#1405000
1!
10
b10111 9
#1410000
0!
00
#1415000
1!
10
b11000 9
#1420000
0!
00
#1425000
1!
10
b11001 9
#1430000
0!
00
#1435000
1!
10
b11010 9
#1440000
0!
00
#1445000
1!
10
b11011 9
#1450000
0!
00
#1455000
1!
10
b11100 9
#1460000
0!
00
#1465000
1!
10
b11101 9
#1470000
0!
00
#1475000
1!
10
b11110 9
#1480000
0!
00
#1485000
1!
10
b11111 9
#1490000
0!
00
#1495000
1!
10
b100000 9
#1500000
0!
00
#1505000
1!
10
b100001 9
#1510000
0!
00
#1515000
1!
10
b100010 9
#1520000
0!
00
#1525000
1!
10
b100011 9
#1530000
0!
00
#1535000
1!
10
b100100 9
#1540000
0!
00
#1545000
1!
10
b100101 9
#1550000
0!
00
#1555000
1!
10
b100110 9
#1560000
0!
00
#1565000
1!
10
b100111 9
#1570000
0!
00
#1575000
1!
10
b101000 9
#1580000
0!
00
#1585000
1!
10
b101001 9
#1590000
0!
00
#1595000
1!
10
b101010 9
#1600000
0!
00
#1605000
1!
10
b101011 9
#1610000
0!
00
#1615000
1!
10
b101100 9
#1620000
0!
00
#1625000
1!
10
b101101 9
#1630000
0!
00
#1635000
1!
10
b101110 9
#1640000
0!
00
#1645000
1!
10
b101111 9
#1650000
0!
00
#1655000
1!
10
b110000 9
#1660000
0!
00
#1665000
1!
10
b110001 9
#1670000
0!
00
#1675000
1!
10
b110010 9
#1680000
0!
00
#1685000
1!
10
b110011 9
#1690000
0!
00
#1695000
1!
10
b110100 9
#1700000
0!
00
#1705000
1!
10
b110101 9
#1710000
0!
00
#1715000
1!
10
14
18
b0 9
#1720000
0!
00
#1725000
1!
10
04
08
b1 9
b11 D
b11 Q
#1730000
0!
00
#1735000
1!
10
b10 9
#1740000
0!
00
#1745000
1!
10
b11 9
#1750000
0!
00
#1755000
1!
10
b100 9
#1760000
0!
00
#1765000
1!
10
b101 9
#1770000
0!
00
#1775000
1!
10
b110 9
#1780000
0!
00
#1785000
1!
10
b111 9
#1790000
0!
00
#1795000
1!
10
b1000 9
#1800000
0!
00
#1805000
1!
10
b1001 9
#1810000
0!
00
#1815000
1!
10
b1010 9
#1820000
0!
00
#1825000
1!
10
b1011 9
#1830000
0!
00
#1835000
1!
10
b1100 9
#1840000
0!
00
#1845000
1!
10
b1101 9
#1850000
0!
00
#1855000
1!
10
b1110 9
#1860000
0!
00
#1865000
1!
10
b1111 9
#1870000
0!
00
#1875000
1!
10
b10000 9
#1880000
0!
00
#1885000
1!
10
b10001 9
#1890000
0!
00
#1895000
1!
10
b10010 9
#1900000
0!
00
#1905000
1!
10
b10011 9
#1910000
0!
00
#1915000
1!
10
b10100 9
#1920000
0!
00
#1925000
1!
10
b10101 9
#1930000
0!
00
#1935000
1!
10
b10110 9
#1940000
0!
00
#1945000
1!
10
b10111 9
#1950000
0!
00
#1955000
1!
10
b11000 9
#1960000
0!
00
#1965000
1!
10
b11001 9
#1970000
0!
00
#1975000
1!
10
b11010 9
#1980000
0!
00
#1985000
1!
10
b11011 9
#1990000
0!
00
#1995000
1!
10
b11100 9
#2000000
0!
00
#2005000
1!
10
b11101 9
#2010000
0!
00
#2015000
1!
10
b11110 9
#2020000
0!
00
#2025000
1!
10
b11111 9
#2030000
0!
00
#2035000
1!
10
b100000 9
#2040000
0!
00
#2045000
1!
10
b100001 9
#2050000
0!
00
#2055000
1!
10
b100010 9
#2060000
0!
00
#2065000
1!
10
b100011 9
#2070000
0!
00
#2075000
1!
10
b100100 9
#2080000
0!
00
#2085000
1!
10
b100101 9
#2090000
0!
00
#2095000
1!
10
b100110 9
#2100000
0!
00
#2105000
1!
10
b100111 9
#2110000
0!
00
#2115000
1!
10
b101000 9
#2120000
0!
00
#2125000
1!
10
b101001 9
#2130000
0!
00
#2135000
1!
10
b101010 9
#2140000
0!
00
#2145000
1!
10
b101011 9
#2150000
0!
00
#2155000
1!
10
b101100 9
#2160000
0!
00
#2165000
1!
10
b101101 9
#2170000
0!
00
#2175000
1!
10
b101110 9
#2180000
0!
00
#2185000
1!
10
b101111 9
#2190000
0!
00
#2195000
1!
10
b110000 9
#2200000
0!
00
#2205000
1!
10
b110001 9
#2210000
0!
00
#2215000
1!
10
b110010 9
#2220000
0!
00
#2225000
1!
10
b110011 9
#2230000
0!
00
#2235000
1!
10
b110100 9
#2240000
0!
00
#2245000
1!
10
b110101 9
#2250000
0!
00
#2255000
1!
10
14
18
b0 9
#2260000
0!
00
#2265000
1!
10
04
08
b1 9
b100 D
b100 Q
#2270000
0!
00
#2275000
1!
10
b10 9
#2280000
0!
00
#2285000
1!
10
b11 9
#2290000
0!
00
#2295000
1!
10
b100 9
#2300000
0!
00
#2305000
1!
10
b101 9
#2310000
0!
00
#2315000
1!
10
b110 9
#2320000
0!
00
#2325000
1!
10
b111 9
#2330000
0!
00
#2335000
1!
10
b1000 9
#2340000
0!
00
#2345000
1!
10
b1001 9
#2350000
0!
00
#2355000
1!
10
b1010 9
#2360000
0!
00
#2365000
1!
10
b1011 9
#2370000
0!
00
#2375000
1!
10
b1100 9
#2380000
0!
00
#2385000
1!
10
b1101 9
#2390000
0!
00
#2395000
1!
10
b1110 9
#2400000
0!
00
#2405000
1!
10
b1111 9
#2410000
0!
00
#2415000
1!
10
b10000 9
#2420000
0!
00
#2425000
1!
10
b10001 9
#2430000
0!
00
#2435000
1!
10
b10010 9
#2440000
0!
00
#2445000
1!
10
b10011 9
#2450000
0!
00
#2455000
1!
10
b10100 9
#2460000
0!
00
#2465000
1!
10
b10101 9
#2470000
0!
00
#2475000
1!
10
b10110 9
#2480000
0!
00
#2485000
1!
10
b10111 9
#2490000
0!
00
#2495000
1!
10
b11000 9
#2500000
0!
00
#2505000
1!
10
b11001 9
#2510000
0!
00
#2515000
1!
10
b11010 9
#2520000
0!
00
#2525000
1!
10
b11011 9
#2530000
0!
00
#2535000
1!
10
b11100 9
#2540000
0!
00
#2545000
1!
10
b11101 9
#2550000
0!
00
#2555000
1!
10
b11110 9
#2560000
0!
00
#2565000
1!
10
b11111 9
#2570000
0!
00
#2575000
1!
10
b100000 9
#2580000
0!
00
#2585000
1!
10
b100001 9
#2590000
0!
00
#2595000
1!
10
b100010 9
#2600000
0!
00
#2605000
1!
10
b100011 9
#2610000
0!
00
#2615000
1!
10
b100100 9
#2620000
0!
00
#2625000
1!
10
b100101 9
#2630000
0!
00
#2635000
1!
10
b100110 9
#2640000
0!
00
#2645000
1!
10
b100111 9
#2650000
0!
00
#2655000
1!
10
b101000 9
#2660000
0!
00
#2665000
1!
10
b101001 9
#2670000
0!
00
#2675000
1!
10
b101010 9
#2680000
0!
00
#2685000
1!
10
b101011 9
#2690000
0!
00
#2695000
1!
10
b101100 9
#2700000
0!
00
#2705000
1!
10
b101101 9
#2710000
0!
00
#2715000
1!
10
b101110 9
#2720000
0!
00
#2725000
1!
10
b101111 9
#2730000
0!
00
#2735000
1!
10
b110000 9
#2740000
0!
00
#2745000
1!
10
b110001 9
#2750000
0!
00
#2755000
1!
10
b110010 9
#2760000
0!
00
#2765000
1!
10
b110011 9
#2770000
0!
00
#2775000
1!
10
b110100 9
#2780000
0!
00
#2785000
1!
10
b110101 9
#2790000
0!
00
#2795000
1!
10
14
18
b0 9
#2800000
0!
00
#2805000
1!
10
04
08
b1 9
b101 D
b101 Q
#2810000
0!
00
#2815000
1!
10
b10 9
#2820000
0!
00
#2825000
1!
10
b11 9
#2830000
0!
00
#2835000
1!
10
b100 9
#2840000
0!
00
#2845000
1!
10
b101 9
#2850000
0!
00
#2855000
1!
10
b110 9
#2860000
0!
00
#2865000
1!
10
b111 9
#2870000
0!
00
#2875000
1!
10
b1000 9
#2880000
0!
00
#2885000
1!
10
b1001 9
#2890000
0!
00
#2895000
1!
10
b1010 9
#2900000
0!
00
#2905000
1!
10
b1011 9
#2910000
0!
00
#2915000
1!
10
b1100 9
#2920000
0!
00
#2925000
1!
10
b1101 9
#2930000
0!
00
#2935000
1!
10
b1110 9
#2940000
0!
00
#2945000
1!
10
b1111 9
#2950000
0!
00
#2955000
1!
10
b10000 9
#2960000
0!
00
#2965000
1!
10
b10001 9
#2970000
0!
00
#2975000
1!
10
b10010 9
#2980000
0!
00
#2985000
1!
10
b10011 9
#2990000
0!
00
#2995000
1!
10
b10100 9
#3000000
0!
00
#3005000
1!
10
b10101 9
#3010000
0!
00
#3015000
1!
10
b10110 9
#3020000
0!
00
#3025000
1!
10
b10111 9
#3030000
0!
00
#3035000
1!
10
b11000 9
#3040000
0!
00
#3045000
1!
10
b11001 9
#3050000
0!
00
#3055000
1!
10
b11010 9
#3060000
0!
00
#3065000
1!
10
b11011 9
#3070000
0!
00
#3075000
1!
10
b11100 9
#3080000
0!
00
